MANIFEST.in
README.rst
setup.py
django_google_tools.egg-info/PKG-INFO
django_google_tools.egg-info/SOURCES.txt
django_google_tools.egg-info/dependency_links.txt
django_google_tools.egg-info/not-zip-safe
django_google_tools.egg-info/top_level.txt
googletools/__init__.py
googletools/admin.py
googletools/models.py
googletools/test_settings.py
googletools/tests.py
googletools/fixtures/analytics_codes.json
googletools/fixtures/site_verification_codes.json
googletools/fixtures/sites.json
googletools/migrations/0001_initial.py
googletools/migrations/0002_auto__add_field_analyticscode_speed.py
googletools/migrations/__init__.py
googletools/templates/googletools/analytics_code.html
googletools/templates/googletools/site_verification_code.html
googletools/templates/googletools/tests/analytics_code_in.html
googletools/templates/googletools/tests/analytics_code_out_a.html
googletools/templates/googletools/tests/analytics_code_out_b.html
googletools/templates/googletools/tests/site_verification_code_in.html
googletools/templates/googletools/tests/site_verification_code_out_a.html
googletools/templates/googletools/tests/site_verification_code_out_b.html
googletools/templatetags/__init__.py
googletools/templatetags/googletools.py