Metadata-Version: 1.0
Name: django-google-tools
Version: 1.0.0
Summary: Django app for managing Google Analytics and Site Verification codes.
Home-page: http://github.com/camilonova/django-google-tools
Author: Orne Brocaar, Camilo Nova
Author-email: camilo.nova@gmail.com
License: MIT
Keywords: django,analytics,google analytics,verification code,site verification
Platform: UNKNOWN
Classifier: Development Status :: 5 - Production/Stable
Classifier: Environment :: Web Environment
Classifier: Framework :: Django
Classifier: Intended Audience :: Developers
Classifier: License :: OSI Approved :: MIT License
Classifier: Operating System :: OS Independent
Classifier: Programming Language :: Python
Classifier: Topic :: Internet :: WWW/HTTP
